pkilint/__init__.py
pkilint/cli_util.py
pkilint/document.py
pkilint/finding_filter.py
pkilint/loader.py
pkilint/oid.py
pkilint/report.py
pkilint/util.py
pkilint/validation.py
pkilint/adobe/__init__.py
pkilint/adobe/adobe_validator.py
pkilint/adobe/asn1/__init__.py
pkilint/bin/__init__.py
pkilint/bin/lint_cabf_serverauth_cert.py
pkilint/bin/lint_cabf_smime_cert.py
pkilint/bin/lint_crl.py
pkilint/bin/lint_etsi_cert.py
pkilint/bin/lint_ocsp_response.py
pkilint/bin/lint_pkix_cert.py
pkilint/bin/lint_pkix_signer_signee_cert_chain.py
pkilint/cabf/__init__.py
pkilint/cabf/cabf_ca.py
pkilint/cabf/cabf_crl.py
pkilint/cabf/cabf_extension.py
pkilint/cabf/cabf_key.py
pkilint/cabf/cabf_name.py
pkilint/cabf/asn1/__init__.py
pkilint/cabf/asn1/ev_guidelines.py
pkilint/cabf/serverauth/__init__.py
pkilint/cabf/serverauth/serverauth_ca.py
pkilint/cabf/serverauth/serverauth_constants.py
pkilint/cabf/serverauth/serverauth_cross_ca.py
pkilint/cabf/serverauth/serverauth_extension.py
pkilint/cabf/serverauth/serverauth_finding_filter.py
pkilint/cabf/serverauth/serverauth_key.py
pkilint/cabf/serverauth/serverauth_name.py
pkilint/cabf/serverauth/serverauth_ocsp.py
pkilint/cabf/serverauth/serverauth_root.py
pkilint/cabf/serverauth/serverauth_subscriber.py
pkilint/cabf/smime/__init__.py
pkilint/cabf/smime/smime_constants.py
pkilint/cabf/smime/smime_extension.py
pkilint/cabf/smime/smime_key.py
pkilint/cabf/smime/smime_name.py
pkilint/cabf/smime/smime_validity.py
pkilint/common/__init__.py
pkilint/common/alternative_name.py
pkilint/common/common_name.py
pkilint/common/organization_id.py
pkilint/etsi/__init__.py
pkilint/etsi/en_319_411_1.py
pkilint/etsi/en_319_412_1.py
pkilint/etsi/en_319_412_2.py
pkilint/etsi/en_319_412_3.py
pkilint/etsi/en_319_412_4.py
pkilint/etsi/en_319_412_5.py
pkilint/etsi/etsi_constants.py
pkilint/etsi/etsi_finding_filter.py
pkilint/etsi/etsi_shared.py
pkilint/etsi/ts_119_312.py
pkilint/etsi/ts_119_495.py
pkilint/etsi/asn1/__init__.py
pkilint/etsi/asn1/en_319_411_1.py
pkilint-0.13.1.dist-info/licenses/LICENSE
pkilint-0.13.1.dist-info/METADATA
pkilint-0.13.1.dist-info/WHEEL
pkilint-0.13.1.dist-info/entry_points.txt
pkilint-0.13.1.dist-info/top_level.txt
pkilint-0.13.1.dist-info/zip-safe
pkilint-0.13.1.dist-info/RECORD
