Metadata-Version: 2.4
Name: pkilint
Version: 0.13.1
Summary: A framework for verifying PKI structures
Home-page: https://github.com/digicert/pkilint
Author: DigiCert, Inc.
Author-email: corey.bonnell@digicert.com
License: MIT
Platform: any
Classifier: Development Status :: 5 - Production/Stable
Classifier: Intended Audience :: Information Technology
Classifier: License :: OSI Approved :: MIT License
Classifier: Operating System :: OS Independent
Classifier: Programming Language :: Python :: 3
Classifier: Programming Language :: Python :: 3 :: Only
Classifier: Programming Language :: Python :: 3.10
Classifier: Programming Language :: Python :: 3.11
Classifier: Programming Language :: Python :: 3.12
Classifier: Programming Language :: Python :: 3.13
Classifier: Programming Language :: Python :: 3.14
Requires-Python: >=3.10
License-File: LICENSE
Requires-Dist: pyasn1
Requires-Dist: pyasn1-alt-modules>=0.4.3
Requires-Dist: pyasn1-fasder<0.2
Requires-Dist: cryptography>=39
Requires-Dist: iso3166
Requires-Dist: validators==0.22
Requires-Dist: python-dateutil
Requires-Dist: publicsuffixlist
Requires-Dist: iso4217
Requires-Dist: python-iso639
Provides-Extra: rest
Requires-Dist: fastapi; extra == "rest"
Provides-Extra: dev
Requires-Dist: pytest; extra == "dev"
Requires-Dist: fastapi; extra == "dev"
Requires-Dist: httpx<1; extra == "dev"
Requires-Dist: black; extra == "dev"
Dynamic: license-file
